ansible_bender/__init__.py
ansible_bender/__main__.py
ansible_bender/api.py
ansible_bender/builder.py
ansible_bender/cli.py
ansible_bender/conf.py
ansible_bender/constants.py
ansible_bender/core.py
ansible_bender/db.py
ansible_bender/exceptions.py
ansible_bender/okd.py
ansible_bender/schema.py
ansible_bender/utils.py
ansible_bender/builders/__init__.py
ansible_bender/builders/base.py
ansible_bender/builders/buildah_builder.py
ansible_bender/callback_plugins/__init__.py
ansible_bender/callback_plugins/snapshoter.py
ansible_bender-0.10.1.dist-info/LICENSE
ansible_bender-0.10.1.dist-info/METADATA
ansible_bender-0.10.1.dist-info/WHEEL
ansible_bender-0.10.1.dist-info/entry_points.txt
ansible_bender-0.10.1.dist-info/top_level.txt
ansible_bender-0.10.1.dist-info/RECORD
