Metadata-Version: 2.1
Name: ansible-bender
Version: 0.10.1
Summary: A tool which builds container images using Ansible playbooks
Home-page: https://github.com/ansible-community/ansible-bender
Author: Tomas Tomecek
Author-email: tomas@tomecek.net
License: MIT
Keywords: ansible,containers,linux,buildah
Classifier: Development Status :: 5 - Production/Stable
Classifier: Environment :: Console
Classifier: Intended Audience :: Developers
Classifier: License :: OSI Approved :: MIT License
Classifier: Operating System :: POSIX :: Linux
Classifier: Programming Language :: Python
Classifier: Programming Language :: Python :: 3.6
Classifier: Programming Language :: Python :: 3.7
Classifier: Programming Language :: Python :: 3.8
Classifier: Programming Language :: Python :: 3.9
Classifier: Programming Language :: Python :: 3.10
Classifier: Programming Language :: Python :: 3.11
Classifier: Topic :: Software Development
Classifier: Topic :: Utilities
Requires-Python: >=3.6
License-File: LICENSE
Requires-Dist: PyYAML
Requires-Dist: tabulate
Requires-Dist: jsonschema
Requires-Dist: setuptools
Provides-Extra: testing
Requires-Dist: pytest ; extra == 'testing'
Requires-Dist: flexmock ; extra == 'testing'
Requires-Dist: pytest-cov ; extra == 'testing'
